MANIFEST.in
README.md
setup.py
./README.md
Finance_Portageur.egg-info/PKG-INFO
Finance_Portageur.egg-info/SOURCES.txt
Finance_Portageur.egg-info/dependency_links.txt
Finance_Portageur.egg-info/requires.txt
Finance_Portageur.egg-info/top_level.txt
portageur/__init__.py
portageur/api/__init__.py
portageur/api/auth.py
portageur/api/chain.py
portageur/api/models.py
portageur/api/prompt.py
portageur/api/serper.py
portageur/kdutils/__init__.py
portageur/kdutils/code.py
portageur/kdutils/exception.py
portageur/kdutils/logger.py
portageur/kdutils/singleton.py
portageur/kdutils/division/__init__.py
portageur/kdutils/division/lazy.py
portageur/plugins/__init__.py
portageur/plugins/agents/__init__.py
portageur/plugins/agents/agent.py
portageur/plugins/agents/tools.py
portageur/plugins/auth/__init__.py
portageur/plugins/auth/azure.py
portageur/plugins/auth/base.py
portageur/plugins/auth/openai.py
portageur/plugins/callback/__init__.py
portageur/plugins/callback/agent_callback.py
portageur/plugins/callback/azure_callback.py
portageur/plugins/callback/chain_callback.py
portageur/plugins/callback/llm_callback.py
portageur/plugins/callback/entity/__init__.py
portageur/plugins/callback/entity/agent_loop.py
portageur/plugins/callback/entity/chain.py
portageur/plugins/callback/entity/message.py
portageur/plugins/chain/__init__.py
portageur/plugins/chain/news.c
portageur/plugins/chain/news.pyx
portageur/plugins/chain/concerns/__init__.py
portageur/plugins/chain/concerns/delayed.py
portageur/plugins/chain/concerns/immediate.py
portageur/plugins/chain/empolyee/__init__.py
portageur/plugins/chain/empolyee/delayed.py
portageur/plugins/chain/empolyee/immediate.py
portageur/plugins/chain/qa/__init__.py
portageur/plugins/chain/qa/immediate.py
portageur/plugins/chain/qa/immediate_memory.py
portageur/plugins/loader/__init__.py
portageur/plugins/loader/employee.py
portageur/plugins/loader/hybrid_weaviate.py
portageur/plugins/loader/seleya_employee.py
portageur/plugins/loader/seleya_news.py
portageur/plugins/memory/__init__.py
portageur/plugins/memory/history.py
portageur/plugins/models/__init__.py
portageur/plugins/models/base.py
portageur/plugins/models/chat_models.py
