Metadata-Version: 2.1
Name: Finance-Portageur
Version: 0.1.8
Summary: Portageur0.1.8
Home-page: https://github.com/flaght
Author: flaght
Author-email: flaght@gmail.com
Requires-Dist: pandas==2.0.3
Requires-Dist: openai==0.27.7
Requires-Dist: langchain==0.0.322
Requires-Dist: requests_html
Requires-Dist: boilerpy3==1.0.6
Requires-Dist: sqlalchemy==2.0.17
Requires-Dist: htmldate==1.4.3
Requires-Dist: tiktoken==0.3.3
Requires-Dist: pymongo==4.4.0
Requires-Dist: gevent==22.10.2
Requires-Dist: tabulate==0.9.0
Requires-Dist: joblib==1.3.1
